{"v":"5.6.6","ip":0,"op":80,"fr":60,"w":60,"h":60,"layers":[{"ind":328,"nm":"surface993","ao":0,"ip":0,"op":80,"st":0,"ty":4,"ks":{"o":{"a":0,"k":100,"ix":11},"r":{"a":1,"k":[{"i":{"x":[0.83],"y":[1]},"o":{"x":[0.17],"y":[0]},"t":0,"s":[0]},{"i":{"x":[0.53],"y":[1]},"o":{"x":[0.6],"y":[0]},"t":11,"s":[-10]},{"i":{"x":[0.83],"y":[1]},"o":{"x":[0.17],"y":[0]},"t":65,"s":[365]},{"i":{"x":[0.83],"y":[1]},"o":{"x":[0.17],"y":[0]},"t":77,"s":[358]},{"t":85,"s":[360]}],"ix":10},"p":{"a":0,"k":[30,30],"ix":2},"a":{"a":0,"k":[22.41,22.41],"ix":1},"s":{"a":0,"k":[133.84,133.85],"ix":6}},"shapes":[{"ty":"gr","hd":false,"nm":"surface993","it":[{"ty":"gr","hd":false,"it":[{"ty":"gr","hd":false,"it":[{"ty":"sh","ks":{"k":{"i":[[0,0],[4.2,-4.2],[0,-5.95],[-4.2,-4.2],[-5.94,0],[-4.21,4.2],[0,5.94],[4.2,4.2],[5.95,0]],"o":[[-5.95,0],[-4.2,4.2],[0,5.95],[4.2,4.2],[5.95,0],[4.2,-4.2],[0,-5.95],[-4.2,-4.2],[0,0]],"v":[[22.41,0],[6.57,6.57],[0,22.41],[6.57,38.26],[22.41,44.82],[38.27,38.26],[44.83,22.41],[38.26,6.57],[22.41,0]],"c":true}}},{"ty":"sh","ks":{"k":{"i":[[0,0],[5.98,0.79],[3.02,5.23],[-2.31,5.58],[-5.83,1.56],[-4.79,-3.68],[0,-6.04],[3.64,-3.64]],"o":[[-4.27,4.27],[-5.98,-0.79],[-3.02,-5.23],[2.31,-5.57],[5.83,-1.56],[4.79,3.68],[0,5.15],[0,0]],"v":[[36.14,36.14],[19.88,41.66],[5.6,32.12],[4.48,14.98],[17.39,3.66],[34.23,7.01],[41.82,22.41],[36.14,36.14]],"c":true}}},{"ty":"fl","o":{"k":100},"c":{"k":[0,0.77,1,1]}},{"ty":"tr","o":{"k":100},"r":{"k":0},"p":{"k":[0,0]},"a":{"k":[0,0]},"s":{"k":[100,100]},"sk":{"k":0},"sa":{"k":0},"hd":false}]},{"ty":"tr","o":{"k":100},"r":{"k":0},"p":{"k":[0,0]},"a":{"k":[0,0]},"s":{"k":[100,100]},"sk":{"k":0},"sa":{"k":0},"hd":false}]},{"ty":"gr","hd":false,"it":[{"ty":"sh","ks":{"k":{"i":[[0,0],[0.35,-0.2],[0,-0.41],[0,0],[-0.35,-0.2],[-0.35,0.2],[0,0],[0,0.4],[0.34,0.2]],"o":[[-0.35,-0.21],[-0.35,0.2],[0,0],[0,0.4],[0.35,0.2],[0,0],[0.34,-0.2],[0,-0.4],[0,0]],"v":[[18.98,14.61],[17.85,14.61],[17.29,15.59],[17.29,29.18],[17.85,30.16],[18.98,30.15],[30.49,23.35],[31.05,22.38],[30.49,21.41]],"c":true}}},{"ty":"sh","ks":{"k":{"i":[[0,0],[0,0],[0,0]],"o":[[0,0],[0,0],[0,0]],"v":[[19.54,27.21],[19.54,17.55],[27.71,22.38]],"c":true}}},{"ty":"fl","o":{"k":100},"c":{"k":[0,0.77,1,1]}},{"ty":"tr","o":{"k":100},"r":{"k":0},"p":{"k":[0,0]},"a":{"k":[0,0]},"s":{"k":[100,100]},"sk":{"k":0},"sa":{"k":0},"hd":false}]},{"ty":"tr","o":{"k":100},"r":{"k":0},"p":{"k":[0,0]},"a":{"k":[0,0]},"s":{"k":[100,100]},"sk":{"k":0},"sa":{"k":0},"hd":false}]}]}],"meta":{"g":"LF SVG to Lottie"},"assets":[]}